{
	"packpath": "~/vim/github",
	"plugins": {
		"start": {
			"danilo-augusto": [
				"vim-afterglow"
			],
			"haya14busa": [
				"vim-operator-flashy"
			],
			"itchyny": [
				"lightline.vim",
				"vim-parenmatch"
			],
			"kana": [
				"vim-operator-replace",
				"vim-operator-user",
				"vim-textobj-line",
				"vim-textobj-user"
			],
			"ntpeters": [
				"vim-better-whitespace"
			],
			"rbtnn": [
				"vim-ambiwidth",
				"vim-gloaded",
				"vim-pkgsync",
				"vim-qficonv",
				"vim-textobj-string",
				"vim-vimscript_indentexpr",
				"vim-vimscript_lasterror",
				"vim-vimscript_tagfunc",
				"vimtweak"
			],
			"sgur": [
				"vim-textobj-parameter"
			],
			"thinca": [
				"vim-qfreplace",
				"vim-textobj-between"
			],
			"tomasr": [
				"molokai"
			],
			"tyru": [
				"restart.vim"
			]
		},
		"opt": {
			"cormacrelf": [
				"vim-colors-github"
			],
			"drewtempelmeyer": [
				"palenight.vim"
			],
			"tyrannicaltoucan": [
				"vim-deep-space"
			]
		}
	}
}
